MANIFEST.in
README.md
setup.py
ucloudclient/__init__.py
ucloudclient/client.py
ucloudclient/shell.py
ucloudclient/uexceptions.py
ucloudclient.egg-info/PKG-INFO
ucloudclient.egg-info/SOURCES.txt
ucloudclient.egg-info/dependency_links.txt
ucloudclient.egg-info/entry_points.txt
ucloudclient.egg-info/requires.txt
ucloudclient.egg-info/top_level.txt
ucloudclient/api/__init__.py
ucloudclient/api/shell_action.py
ucloudclient/api/udisk.py
ucloudclient/api/uhost.py
ucloudclient/api/umon.py
ucloudclient/api/unet.py
ucloudclient/tests/__init__.py
ucloudclient/tests/test_client.py
ucloudclient/tests/test_shell.py
ucloudclient/tests/api/__init__.py
ucloudclient/tests/api/shell_action.py
ucloudclient/tests/api/uhost.py
ucloudclient/tests/api/umon.py
ucloudclient/tests/api/unet.py
ucloudclient/tests/utils/__init__.py
ucloudclient/tests/utils/api_utils.py
ucloudclient/tests/utils/args_parameters.py
ucloudclient/tests/utils/encodeutils.py
ucloudclient/tests/utils/shell_utils.py
ucloudclient/tests/utils/test_base.py
ucloudclient/utils/__init__.py
ucloudclient/utils/api_utils.py
ucloudclient/utils/args_parameters.py
ucloudclient/utils/base.py
ucloudclient/utils/encodeutils.py
ucloudclient/utils/shell_utils.py