Metadata-Version: 1.0
Name: ucloudclient
Version: 0.2.0
Summary: Ucloud(Ucloud.cn) python client and command line tools.Author's bolg http://yanheven.github.io
Home-page: https://github.com/yanheven/ucloud-python-sdk
Author: yanhaifeng(颜海峰)
Author-email: yanheven@gmail.com
License: Apache License Version 2.0
Keywords: ucloud,client
Platform: any
